pyregression_GonenRaveh/__init__.py
pyregression_GonenRaveh/pyregression.py
pyregression_package_GonenRaveh-1.0.1.dist-info/LICENSE
pyregression_package_GonenRaveh-1.0.1.dist-info/METADATA
pyregression_package_GonenRaveh-1.0.1.dist-info/WHEEL
pyregression_package_GonenRaveh-1.0.1.dist-info/top_level.txt
pyregression_package_GonenRaveh-1.0.1.dist-info/RECORD
