Metadata-Version: 2.1
Name: pyregression_package_GonenRaveh
Version: 1.0.1
Summary: A small package for Mathematical Regression Solver from Multi Features to a single Target feature
Author-email: Gonen Raveh <gonen.raveh@gmail.com>
License: Copyright (c) 2018 The Python Packaging Authority
Project-URL: Homepage, https://github.com/gonenraveh/pyregression
Classifier: Programming Language :: Python :: 3
Classifier: License :: OSI Approved :: MIT License
Classifier: Operating System :: OS Independent
Requires-Python: >=3.8
License-File: LICENSE
Requires-Dist: numpy
Requires-Dist: scikit-learn
Requires-Dist: matplotlib
